kim/__about__.py
kim/__init__.py
kim/data.py
kim/map.py
kim/.ipynb_checkpoints/__about__-checkpoint.py
kim/.ipynb_checkpoints/__init__-checkpoint.py
kim/.ipynb_checkpoints/map-checkpoint.py
kim/mapping_model/__init__.py
kim/mapping_model/dataloader.py
kim/mapping_model/dataloader_torch.py
kim/mapping_model/loss_func.py
kim/mapping_model/mlp.py
kim/mapping_model/optim.py
kim/mapping_model/optim_ens.py
kim/pre_analysis/__init__.py
kim/pre_analysis/metric_calculator.py
kim/pre_analysis/pairwise_analysis.py
kim/pre_analysis/pc_analysis.py
kim/pre_analysis/pre_analysis.py
kim/pre_analysis/sst.py
kim/utils/__init__.py
kim/utils/metrics.py
kim/utils/plotting.py
kim/utils/scaler.py
kim_jax-1.2.0.dist-info/METADATA
kim_jax-1.2.0.dist-info/WHEEL
kim_jax-1.2.0.dist-info/licenses/LICENSE
kim_jax-1.2.0.dist-info/RECORD
