Metadata-Version: 2.4
Name: kim-jax
Version: 1.2.0
Summary: A package for developing knowledge informed inverse or forward mapping using ensemble learning
Project-URL: Homepage, https://github.com/PeishiJiang/KIM
Author-email: Peishi Jiang <shixijps@gmail.com>
License-Expression: BSD-2-Clause
License-File: LICENSE
Classifier: Operating System :: OS Independent
Classifier: Programming Language :: Python :: 3
Requires-Python: >=3.11
Requires-Dist: equinox
Requires-Dist: hydroeval
Requires-Dist: ipykernel
Requires-Dist: jax
Requires-Dist: joblib
Requires-Dist: jupyter
Requires-Dist: matplotlib
Requires-Dist: numpy
Requires-Dist: optax
Requires-Dist: pandas
Requires-Dist: pytest
Requires-Dist: scikit-learn
Requires-Dist: scipy
Requires-Dist: seaborn
Requires-Dist: torch
Requires-Dist: torchvision
Requires-Dist: tqdm
